streamlit_cld_media_library/__init__.py
streamlit_cld_media_library/frontend/index.html
streamlit_cld_media_library/frontend/main.js
streamlit_cld_media_library/frontend/streamlit-component-lib.js
streamlit_cld_media_library/frontend/style.css
cld_media_library-0.1.0.dist-info/LICENSE
cld_media_library-0.1.0.dist-info/METADATA
cld_media_library-0.1.0.dist-info/WHEEL
cld_media_library-0.1.0.dist-info/top_level.txt
cld_media_library-0.1.0.dist-info/RECORD
