Metadata-Version: 2.1
Name: cld-media-library
Version: 0.1.0
Summary: Import Cloudinary's Media Library Widget as a compoent
Author: Akshay Ranganath
Author-email: akshay.ranganath@cloudinary.com
Requires-Python: >=3.7
License-File: LICENSE
Requires-Dist: streamlit (>=1.2)
Requires-Dist: jinja2
